base_service/__init__.py
base_service/email_worker.py
base_service/exceptions.py
base_service/service.py
base_service/utils.py
base_service/worker.py
miauw_base_service-1.10.0.dist-info/METADATA
miauw_base_service-1.10.0.dist-info/WHEEL
miauw_base_service-1.10.0.dist-info/top_level.txt
miauw_base_service-1.10.0.dist-info/RECORD
