Metadata-Version: 2.1
Name: miauw-base-service
Version: 1.10.0
Summary: base service and base worker class for miauw
Author: cheetahbyte
Author-email: cheetahbyte <contact@cheetahbyte.dev>
Requires-Python: >=3.11
Requires-Dist: aio-pika
Provides-Extra: dev
Requires-Dist: pytest ; extra == 'dev'
